AUTHORS
LICENSE
MANIFEST.in
README.rst
VERSION
rose.py
setup.py
rose.egg-info/PKG-INFO
rose.egg-info/SOURCES.txt
rose.egg-info/dependency_links.txt
rose.egg-info/top_level.txt