Metadata-Version: 1.1
Name: rose
Version: 1.0.0
Summary: A small library for keeping your version up-to-date easily & everywhere.
Home-page: http://github.com/toastdriven/rose
Author: Daniel Lindsley
Author-email: daniel@toastdriven.com
License: BSD
Platform: UNKNOWN
Classifier: Development Status :: 5 - Production/Stable
Classifier: Intended Audience :: Developers
Classifier: License :: OSI Approved :: BSD License
Classifier: Operating System :: OS Independent
Classifier: Topic :: Utilities
Classifier: Programming Language :: Python
Classifier: Programming Language :: Python :: 3
